LICENSE
README.md
setup.py
cinnamon_th/__init__.py
cinnamon_th.egg-info/PKG-INFO
cinnamon_th.egg-info/SOURCES.txt
cinnamon_th.egg-info/dependency_links.txt
cinnamon_th.egg-info/top_level.txt
cinnamon_th/components/__init__.py
cinnamon_th/components/callback.py
cinnamon_th/components/helper.py
cinnamon_th/components/model.py
cinnamon_th/configurations/__init__.py
cinnamon_th/configurations/callback.py
cinnamon_th/configurations/helper.py